tmpbrowse
