Metadata-Version: 1.1
Name: tmpbrowse
Version: 0.0.2
Summary: Spawns a temporary browser session for testing with your app development 
Home-page: https://github.com/sp4ke/tmpbrowse
Author: Chakib Benziane
Author-email: chakib.benz@gmail.com
License: MIT
Keywords: tmpbrowse browser chrome session test web development
Platform: UNKNOWN
Classifier: Development Status :: 3 - Alpha
Classifier: Environment :: Console
Classifier: Intended Audience :: Developers
Classifier: Programming Language :: Python :: 2
Classifier: Programming Language :: Python :: 2.7
Classifier: Topic :: Software Development :: Testing
